{
  "kind": "singleType",
  "collectionName": "mobile_app_home_sections",
  "info": {
    "singularName": "mobile-app-home-section",
    "pluralName": "mobile-app-home-sections",
    "displayName": "Mobile App Home Page Section"
  },
  "options": {
    "draftAndPublish": true
  },
  "pluginOptions": {
    "i18n": {
      "localized": true
    }
  },
  "attributes": {
    "title": {
      "type": "string",
      "pluginOptions": {
        "i18n": {
          "localized": true
        }
      }
    },
    "description": {
      "type": "text",
      "pluginOptions": {
        "i18n": {
          "localized": true
        }
      }
    },
    "quickInfoLabel1": {
      "type": "string",
      "pluginOptions": {
        "i18n": {
          "localized": true
        }
      }
    },
    "quickInfoValue1": {
      "type": "string",
      "pluginOptions": {
        "i18n": {
          "localized": true
        }
      }
    },
    "quickInfoLabel2": {
      "type": "string",
      "pluginOptions": {
        "i18n": {
          "localized": true
        }
      }
    },
    "quickInfoValue2": {
      "type": "string",
      "pluginOptions": {
        "i18n": {
          "localized": true
        }
      }
    },
    "floatingCardLabel": {
      "type": "string",
      "pluginOptions": {
        "i18n": {
          "localized": true
        }
      }
    },
    "floatingCardValue": {
      "type": "string",
      "pluginOptions": {
        "i18n": {
          "localized": true
        }
      }
    },
    "floatingCardDesc": {
      "type": "text",
      "pluginOptions": {
        "i18n": {
          "localized": true
        }
      }
    },
    "mockupTitle": {
      "type": "string",
      "pluginOptions": {
        "i18n": {
          "localized": true
        }
      }
    },
    "mockupDesc": {
      "type": "text",
      "pluginOptions": {
        "i18n": {
          "localized": true
        }
      }
    },
    "phoneImage": {
      "type": "media",
      "pluginOptions": {
        "i18n": {
          "localized": false
        }
      },
      "multiple": false,
      "allowedTypes": [
        "images",
        "files",
        "videos",
        "audios"
      ]
    },
    "features": {
      "type": "component",
      "pluginOptions": {
        "i18n": {
          "localized": true
        }
      },
      "component": "department-sections.shared-simple-feature",
      "repeatable": true
    }
  }
}
